teleoss/__init__.py
teleoss/teleoss.py
teleoss/const/__init__.py
teleoss/const/click_setting.py
teleoss/const/s3cfg.py
teleoss/utils/__init__.py
teleoss/utils/file_utils.py
teleoss-0.1.1.dist-info/METADATA
teleoss-0.1.1.dist-info/WHEEL
teleoss-0.1.1.dist-info/entry_points.txt
teleoss-0.1.1.dist-info/top_level.txt
teleoss-0.1.1.dist-info/RECORD
