Metadata-Version: 2.1
Name: teleoss
Version: 0.1.1
Summary: Command line toolkit for tele oss
Home-page: UNKNOWN
Author: imason
Author-email: moy7@chinatelecom.cn
License: UNKNOWN
Keywords: teleoss
Platform: UNKNOWN
Classifier: Programming Language :: Python :: 3
Classifier: License :: OSI Approved :: MIT License
Classifier: Operating System :: OS Independent
Requires-Python: >=3.6,
Requires-Dist: Click
